outils_de_controles/__init__.py
outils_de_controles/controle_arguments.py
outils_de_controles/verificateur.py
outils_de_controles/verificateur_arguments.py
outils_de_controles/verificateur_conteneurs.py
outils_de_controles/verificateur_listes.py
outils_de_controles/verificateur_str.py
outils_de_controles/verificateur_tableaux.py
outils_de_controles-2.5.3.data/data/Documentation technique outils de controles.pdf
outils_de_controles-2.5.3.data/data/_Guide d'utilisation du package outils de controles.pdf
outils_de_controles-2.5.3.dist-info/LICENSE
outils_de_controles-2.5.3.dist-info/METADATA
outils_de_controles-2.5.3.dist-info/WHEEL
outils_de_controles-2.5.3.dist-info/top_level.txt
outils_de_controles-2.5.3.dist-info/RECORD
