Metadata-Version: 2.1
Name: outils-de-controles
Version: 2.5.3
Summary: Outils_de_controles permet de vérifier que des objets sont valides.
Author-email: Cyprien BONTRON <c.b.e.python@gmail.com>
Maintainer-email: Cyprien BONTRON <c.b.e.python@gmail.com>
License: Creative Commons Attribution-NonCommercial-ShareAlike 4.0 International Public License
Project-URL: Download-URL, https://pypi.org/project/outils-de-controles/
Classifier: Programming Language :: Python :: 3.8
Classifier: Programming Language :: Python :: 3.9
Classifier: Programming Language :: Python :: 3.10
Classifier: Programming Language :: Python :: 3.11
Classifier: Natural Language :: French
Classifier: Intended Audience :: Developers
Classifier: License :: Free for non-commercial use
Classifier: Development Status :: 5 - Production/Stable
Requires-Python: >=3.8
License-File: LICENSE
